caronte_infra/database/config/mongo_document.py
caronte_infra/database/connection/mongo_connection.py
caronte_api_infra-0.1.0.dist-info/LICENSE
caronte_api_infra-0.1.0.dist-info/WHEEL
caronte_api_infra-0.1.0.dist-info/METADATA
caronte_api_infra-0.1.0.dist-info/RECORD
