Metadata-Version: 2.1
Name: caronte-api-infra
Version: 0.1.0
Summary: Infraestructure package to integrate services
License: GNU
Author: Giovani Liskoski Zanini
Author-email: giovanilzanini@hotmail.com
Requires-Python: >=3.9,<4.0
Classifier: License :: Other/Proprietary License
Classifier: Programming Language :: Python :: 3
Classifier: Programming Language :: Python :: 3.9
Classifier: Programming Language :: Python :: 3.10
Classifier: Programming Language :: Python :: 3.11
Requires-Dist: caronte-api-common (>=0.2.0,<0.3.0)
Requires-Dist: motor (>=3.1.1,<4.0.0)
Requires-Dist: pydantic (>=1.10.4,<2.0.0)
